cborJ/__init__.py
cborJ/__main__.py
cborJ/cbor_decoder.py
cborJ/cbor_encoder.py
cborj-0.1.1.dist-info/METADATA
cborj-0.1.1.dist-info/WHEEL
cborj-0.1.1.dist-info/entry_points.txt
cborj-0.1.1.dist-info/licenses/LICENSE
cborj-0.1.1.dist-info/RECORD
